{"language": "Latin", "author": "\"Angelus, Christophorus, d. 1638\"", "title": "\"De statu hodiernorum Gr\u00becorum enchiridion Christophori Angeli Gr\u00beci Gr\u00bece conscriptum, jam correcti\u009ds cum versione Latin\u0089 \u008f regione posit\u0089 & annotationibus mult\u0098 qv\u0088m antehac locupletioribus, cur\u0089 Georgii Fehlavii, ..\"", "pub_loc": "Leipzig", "imprint": "\"Lipsi\u00be: aimpensis Johannis Grossii et socii. Stanno Coleriano, 1676\"", "pub_year": "1666", "id": "16114"}