{"imprint": "\"t'Amsterdam,: by Jacob van Meurs ..., 1661 t'Amsterdam ter drukkerye van Steven van Lier ...\"", "pubYear": "1661", "prqId": "ned-kbn-all-00004304-001", "language": "Dutch", "title": "Afbeelding van 't oude Romen, waar in vertoont worden de voornaamste tempelen, schouburgen ... gewoonten, plichten, en andere gedenkwaerdige saken. Als ook een beschryving van de grootheit des Roomschen gebieds. Alles met 128. \u00e7ierlijke kopere platen, den", "author": "Totti, Pompilio", "id": "24288", "pubLoc": "Amsterdam"}