{"language": "French", "author": "\"Raynaud, Th\u008eophile, 1583-1663\"", "title": "\"Trait\u008e des fievres malignes et pourpr\u008ees; dans lequel on propose un syst\u008eme nouveau sur la nature de ces m\u0090mes fi\u008evres, qui explique m\u008ecaniquement tous les symptomes; d'o\u009d resulte la maniere pr\u008ecise de les gu\u008erir non pas par l'usage de la saign\u008ee, des aci\"", "pub_loc": "Carpentras", "imprint": "\"Carpentras: Barthelemy Ravasi, 1695\"", "pub_year": "1695", "id": "28291"}