{"language": "Danish", "author": "\"N\u00bfrnissom, Jens S\u00bfrensen\"", "title": "\"En kort Beskriffvelse om de f\u00bfrste Kircker, som bleffve med H\u00bender giort paa Jorden, oc hvorledis Danske-mend fick f\u00bfrst Christi Kundskab Disligest: Om de hellige Apostlers oc Helgens Historie ... nu kortelig ... colligeret oc sammen skreffvet, aff Jens S\"", "pub_loc": "K\u00bfbenhavn", "imprint": "\"Ki\u00bfbenh.: prentet ... af Christen Jens\u00bfn, 1660\"", "pub_year": "1660", "id": "28641"}