{"imprint": "\"[Wittenberg]: excudebat Johannes R\u00f6hnerus, 1648\"", "pubYear": "1648", "prqId": "den-kbd-all-11030400489B-001", "language": "Latin", "title": "In Augustan\u00e6 Confessionis articuli primi partem posteriorem, qu\u00e6 est secunda. De operibus primi diei, et qsysidem in specie de luce ex Becano & contra eundem quam Witteberg\u00e6 pr\u00e6side Jacobo Martini ... in Auditorio Theologico public\u00e8 sibi defendendam susci", "author": "Martini, Jakob, 1570-1649", "id": "28913", "pubLoc": "Wittenberg"}