{"language": "Latin", "author": "Lapide, Jean Heynlin, connu sous le nom de Joannes de (chartreux)", "title": "Resolutorium dubiorum. Venundantur Parisius a Johanne Lamberto, residenti in vico Brunello, sub imagine divi Claudii. - Au v\u00b0 du titre : Resolutorium dubiorum circa celebrationem missarum occurrentium, per venerabilem patrem dominum Johannem de Lapide,.", "pub_loc": "Paris", "imprint": "\"Venundantur Parisius a Johanne Lamberto, residenti in vico Brunello, sub imagine divi Claudii\"", "pub_year": "1513", "id": "32970"}