{"language": "French", "author": "Machault, Jean Baptiste de, 1591-1640", "title": "Histoire de ce qui s'est pass\u008e \u008fs royaumes du Japon, & de la Chine. Tir\u008ee des lettres escrites \u008fs ann\u008ees 1621 & 1622. Adress\u008ees au R. P. Mutio Vitelleschi g\u008en\u008eral de la Compagnie de J\u008esus. Traduite de l'italien en fran\u008dois, par un P\u008fre de la mesme compagn", "pub_loc": "Paris", "imprint": "\"A Paris, chez S\u008ebastien Cramoisy. M. DC. XXVII\"", "pub_year": "1627", "id": "34084"}