{"imprint": "\"Lvgdvni Batavorvm: ex officin\u00e2 Davidis Lopez de Haro, 1656\"", "pubYear": "1656", "imagePath": "ned-kbn-all-00002895-001-0002R_96.jpg", "prqId": "ned-kbn-all-00002895-001", "language": "Latin", "title": "Jacobi Baselii ecclesiast\u00e6 Kerckwerviensis, Sulpitius Belgicvs, sive historia religionis, instaurat\u00e6e, corrupt\u00e6 & reformat\u00e6 in Belgio & \u00e0 Belgis \u00e0 nato Christo ad annum CI[reverse C] I[reverse C]", "author": "Baselius, Jacobus, 1563-1604", "id": "10270", "pubLoc": "Leiden"}