{"imprint": "\"Rouen: Jean Baptiste Behourt, 1628\"", "pubYear": "1628", "imagePath": "/images/hin-wel-all-00000995-001-0001R_96.jpg", "prqId": "hin-wel-all-00000995-001", "language": "French", "title": "Quatre livres des secrets de medecine et de la philosophie chimique / Faicts fran\u00e7ois par M. Jean Liebaut ... Esquels sont descrits plusieurs remedes singuliers pour toutes maladies tant interieures qu'exterieures du corps humain ... les manieres de desti", "author": "Gessner, Conrad, 1516-1565", "id": "11240", "pubLoc": "Rouen"}