{"imprint": "\"[London]: [apud Iohannem Billium], [1617]\"", "pubYear": "1617", "imagePath": "ita-bnc-mag-00002299-001-0004R_96.jpg", "prqId": "ita-bnc-mag-00002299-001", "language": "Latin", "title": "Miscellaneorum theologicorum. Quibus non modo Scriptur\u00e6 Diuin\u00e6, sed & aliorum classicorum auctorum plurima monumenta explicantur atque illustrantur; libris tres, plurimarum observationum, in hac editione insigni auctario locupletati: His insuper accessit,", "author": "Fuller, Nicholas, 1557-1626", "id": "12939", "pubLoc": "London"}