{"imprint": "\"Neapoli: ex typographia Ioannis Francisci Paci, 1683\"", "pubYear": "1683", "imagePath": "ita-bnc-mag-00002313-001-0004R_96.jpg", "prqId": "ita-bnc-mag-00002313-001", "language": "Latin", "title": "De actibus humanis, eorumque differentijs, & proprietatibus, libri tres. Additis duabus elucubrationibus, altera contra vsum probabilitatum, altera contra nonam propositionem damnatam in Decreto SS.D.N. 2. Martij 1679. Authore fr. Bartholomaeo Riccio Neap", "author": "Ricci, Bartolomeo, 1542-1613", "id": "14528", "pubLoc": "Napoli"}