{"imprint": "\"Witeberg\u00e6: typis Zachari\u00e6 Cratonis, 1587\"", "pubYear": "1587", "imagePath": "/images/den-kbd-all-130018157080-001-0002R_96.jpg", "prqId": "den-kbd-all-130018157080-001", "language": "Latin", "title": "Historia Michaelis Boiemi de somniis eorumque eventibus ad Henricum Ranzovium ... cujus elegia de somniis in fine huius opusculi adiceta est, una cum genealogia famili\u00e6 Ranzovian\u00e6 ... ab eodem Michaele Boiemo", "author": "", "id": "15202", "pubLoc": "Wittenberg"}