{"imprint": "\"Rostog: durch Stephan M\u00fcllman gedruckt, 1586\"", "pubYear": "1586", "imagePath": "/images/den-kbd-all-130017588967-001-0002R_96.jpg", "prqId": "den-kbd-all-130017588967-001", "language": "German", "title": "Trostpredigt Bey der F\u00fcrstlichen Leiche, Der Durchleuchtigen Hochbebornen F\u00fcrstin und Frawen, Fraw Elisabeth, geborn aus K\u00f6niglichem stam zu Dennemarcken etc. Hertzogin zu Meckelnburg ... Zu Schwan im Hertzogthumb Meckelnburg, Anno 1586. den 23. Octobris,", "author": "Pauli, Simon", "id": "15238", "pubLoc": "Rostock"}