{"imprint": "\"Lugduni-Batavorum: Apud Franciscos Hegerum & F. Hackium, 1639\"", "pubYear": "1639", "imagePath": "/images/hin-wel-all-00003083-001-0004R_96.jpg", "prqId": "hin-wel-all-00003083-001", "language": "Latin", "title": "De integritatis et corruptionis virginum notis: de graviditate et partu naturali mulierum / Ludov. Bonacioli Enneas muliebris ... Fel. Plateri ... De origine partium, earumque in utero conformatione. Pet. Gassendi De septo cordis pervio, observationes", "author": "Pineau, S\u00e9verin, d. 1619", "id": "19119", "pubLoc": "Leiden"}