{"imprint": "\"Aurillac: Par Estienne Boris imprimeur & marchand libraire, 1648.\"", "pubYear": "1648", "imagePath": "hin-wel-all-00002678-001-0002R_96.jpg", "prqId": "hin-wel-all-00002678-001", "language": "French", "title": "Traicte tres-necessaire a ceux qui desirent boire les eaux de Vic :bavec le regime qu'il faut tenir pour uses desdites eaux, & a quelle maladies, elles sont utiles, ou dangereuses, chose tres approuv\u00e9e / Precieux present que Jean Mante a faict aux valetud", "author": "Mante, Jean", "id": "19380", "pubLoc": "Aurillac"}