{"imprint": "\"Francofurti: Apud heredes Andreae Wecheli, Claudium Marnium, & Joannem Aubrium, 1597\"", "pubYear": "1597", "imagePath": "/images/hin-wel-all-00002572-001-0002R_96.jpg", "prqId": "hin-wel-all-00002572-001", "language": "Latin", "title": "De febribus liber: genera, causas, et curationes febrium tribus capitibus proponens ... Adjunctis insuper historiis viginti: curationes febrium praecipuorum generum, morborumque quorundam febres comitari subsequique solitorum, describentibus / [Felix Plat", "author": "Platter, Felix, 1536-1614", "id": "19898", "pubLoc": "Frankfurt"}