{"imprint": "\"In Padova: per Pietro Maria Frambotto, 1682\"", "pubYear": "1682", "imagePath": "ned-kbn-all-00007128-001-0006R_96.jpg", "prqId": "ned-kbn-all-00007128-001", "language": "Italian", "title": "Copia di lettera scritta all' illustrissimo Signore Antonio Magliabechi bibliotecario del Grand Duca di Toscana intorno alla nuova cometa apparsa quest' anno 1682, sotto i piedi dell'Orsa Maggiore Geminiano Montanari, astronomo, e meteorologo dello studio", "author": "Montanari, Geminiano, 1633-1687", "id": "24196", "pubLoc": "Padova"}