{"imprint": "\"Tot Leeuwarden,: gedruckt by Gysbert Sybes, 1659\"", "pubYear": "1659", "imagePath": "ned-kbn-all-00005746-001-0002R_96.jpg", "prqId": "ned-kbn-all-00005746-001", "language": "Dutch", "title": "Statuten, ordonnantien, ende costumen van Frieslandt, ten bevele, van de heeren Staten, des selven landts, by een vergadert; ende op nieuws, met veele nieuwe resolutien ... so by de Staten van't landt gearresteert ende gedecreteert sijn, insonder mede op", "author": "", "id": "25577", "pubLoc": "Leeuwarden"}