{"imprint": "\"Corrigerit oc rettet effter Autoris egen haand oc siden tryct i Aarhus=\u00c5rhus, 1639\"", "pubYear": "1639", "imagePath": "/images/den-kbd-all-110508012923-002-0001R_96.jpg", "prqId": "den-kbd-all-110508012923-002", "language": "Danish", "title": "Troens Triumph oc Seyer : det er, Tr\u00f8st mod Troens Suaghed , oc grundelig Bevissning, at de Gudfryctige bliffue aff Guds Mact bevarede .... Beskreffuen ved Niels Laurits\u00f8n ...", "author": "", "id": "29235", "pubLoc": "Aarhus"}