{"imprint": "\"Parisiis : venundantur apud Simonem Le Moyne, 1635\"", "pubYear": "1635", "imagePath": "hin-wel-all-00010049-001-0002R_96.jpg", "prqId": "hin-wel-all-00010049-001", "language": "Latin", "title": "Iac. Cornvti ... Canadensivm planatarvm, aliar&#250;mque nondum editarum historia. Cui adiectum est ad calcem enchiridion botanicvm Parisiense. Continens indicem plantarum, quae in pagis, siluis, pratis, et montosis iuxta Parisios locis nascuntur / [Jacqu", "author": "", "id": "29569", "pubLoc": "Paris"}