{"imprint": "\"Ilz se vendent \u00e0 paris, en la rue Sainct-Jacques\"", "pubYear": "1522", "imagePath": "/images/fra-bnf-rlr-00004279-001-0002R_96.jpg", "prqId": "fra-bnf-rlr-00004279-001", "language": "French", "title": "La L\u00e9gende des Flamens artisiens et haynuyers, ou autrement leur cronique abregee, en laquelle sont contenues plusieurs histoires de France, Angleterre et Allemaigne. Avecques les genealogies et descentes des roys de Naples et Sicille qui y ont regne en q", "author": "", "id": "31410", "pubLoc": "Paris"}