{"imprint": "", "pubYear": "1659", "imagePath": "fra-bnf-rlr-00002337-001-0006R_96.jpg", "prqId": "fra-bnf-rlr-00002337-001", "language": "French", "title": "La Liste de Messieurs les gardes et anciens gardes de l'orph\u00e8vrerie de Paris. La Liste des marchands maistres orph\u00e8vres \u00e0 Paris. Celle des gouverneurs de la Confrairie de Nostre-Dame du Blancmesnil. Celle de la Confrairie de Ste Anne fond\u00e9e en l'\u00e9glise No", "author": "Berquen, Robert de", "id": "34188", "pubLoc": ""}