{"imprint": "\"Francofurti [Frankfurt am Main] : apud. A. Wechelum, 1581\"", "pubYear": "1581", "imagePath": "/images/hin-wel-all-00009009-001-0003R_96.jpg", "prqId": "hin-wel-all-00009009-001", "language": "Latin", "title": "Natalis Comitis Mythologi\u00e6, sive explicationum fabularum libri decem. In quibus omnia prop\u00e8 naturalis & moralis philosophi\u00e6 dogmata contenta fuisse demonstratur / nuper ab ipso autore recogniti & locupletati. Eiusdem Libri quatuor de venatione ...", "author": "Conti, Natale, 1520-1582", "id": "34688", "pubLoc": "Frankfurt am Main"}