{"imprint": "\"[Lvgdvni Batavorum] : ex officina Plantiniana, apvd Christophorvm Raphelengivm, Academiae lugduno-batauae typographum [exp. J. Commelini] M.D.C.\"", "pubYear": "1600", "imagePath": "/images/hin-wel-all-00010140-001-0004R_96.jpg", "prqId": "hin-wel-all-00010140-001", "language": "Latin", "title": "M. ManilI Astronomicon a Iosepho Scaligero ex vetusto codice Gemblacensi infinitis mendis repurgatum. Eivsdem Iosephi Scaligeri notae, quibus auctoris prisca astrologia explicatur, castigationum caussae redduntur, portentosae transpositiones in eo auctore", "author": "Manilius, Marcus, fl. 9 A.D.", "id": "34707", "pubLoc": "Leiden"}