{"imprint": "\"Amstelodami: apud G. Trigg, 1651\"", "pubYear": "1651", "imagePath": "/images/hin-wel-all-00004968-001-0006R_96.jpg", "prqId": "hin-wel-all-00004968-001", "language": "Latin", "title": "Equitis Franci et adolescentul\u00e6 mulieris Ital\u00e6 practica artis amandi, insigni et jucvndissima historia ostensa / [auctore \u00c6nea Sylvio Piccolomini] Cui praeterea, qu\u00e6 ex variis autoribus antehac annexa sunt, alia qu\u00e6dam huic materi\u00e6 non inconvenientia jam", "author": "Drudo, Hilarius, pseud.", "id": "35601", "pubLoc": "Amsterdam"}