{"imprint": "\"Hamburgi: apud Gothofredum Schultz ; Prostant Amsterodami: apud Joannem Janssonium \u00e0 Waesberge, 1673\"", "pubYear": "1673", "imagePath": "hin-wel-all-00003860-001-0006R_96.jpg", "prqId": "hin-wel-all-00003860-001", "language": "Latin", "title": "Specimen de gemmarum origine et virtutibus. In quo proponuntur et historic\u00e8 illustrantur quaedam conjecturae circa consistentiam materiae lapidum praetiosorum, et subjecta, in quibus eorum praecipuae virtutes consistunt. Primum Anglic\u00e8 conscriptum authore", "author": "Boyle, Robert, 1627-1691", "id": "36029", "pubLoc": "Hamburg"}