{"imprint": "\"Hafni\u00e6: literis Christiani Weringii, 1689-1691\"", "pubYear": "1689", "imagePath": "/images/den-kbd-all-111404010145-001-0001R_96.jpg", "prqId": "den-kbd-all-111404010145-001", "language": "Latin", "title": "Horometria logo-lesbia, i.e. terminorum mensura logicorum a re exacta, per restrictionem materialis identica, ceu qva pr\u00e6dicatum reapse idem est cum materia, vel subjecto suo, per abstractionem formalis eccliptica, ceu qva forma pr\u00e6dicati, a re sine re, i", "author": "Hjort (Cervinus), Ludvig Lauridsen", "id": "38009", "pubLoc": "K\u00f8benhavn"}