{"imprint": "\"Haarlem: Gillis Rooman, voor Jan Evertsz Cloppenburch te Amsterdam, 1589\"", "pubYear": "1589", "imagePath": "/images/ned-kbn-all-00010714-001-0002R_96.jpg", "prqId": "ned-kbn-all-00010714-001", "language": "Dutch", "title": "De wortel, den oorspronck ende het fundament der Wederdooperen, oft Herdooperen van onsen tijde ... wt der Fransoyscher talen ... ouergheset door J.D.R. ende nu wederom ouersien ende ... verrijckt", "author": "Br\u00e8s, Guy de, 1522-1567", "id": "40914", "pubLoc": "Haarlem"}