{"imprint": "Venetijs apud Federicum Turrisanum 1549.", "pubYear": "1549", "imagePath": "ita-bnc-ald-00000398-001-0001R_96.jpg", "prqId": "ita-bnc-ald-00000398-001", "language": "Greek", "title": "Erotemata tou Chrysolora. Peri anomalon rematon. Peri schematismou ton chronon ek ton chalkondylou. To tetarton tou gaze, peri syntaxeos. Peri enkletikon. Gnomai monostichoi ek diaphoron poieton. Katon. Erotemata tou Gouarinou. Erotemata Chrysolorae. De a", "author": "Chrysoloras, Manuel, ca. 1350-1415", "id": "5164", "pubLoc": "Venezia"}