{"imprint": "\"'t Amsterdam: Door Jan Hendriksz en Jan Rieuwerts, 1654\"", "pubYear": "1654", "imagePath": "ned-kbn-all-00001470-001-0006R_96.jpg", "prqId": "ned-kbn-all-00001470-001", "language": "Dutch", "title": "De vermaarde reizen van de heer Vincent le Blanc van Marsilien, Die hy sedert d'ouderdom van veertien jaren, tot aan die van zestig, in de vier delen des werrelts gedaan heeft; te weten in Oost- en Westindien, in Persien, Arabien, Pegu, en in meest alle d", "author": "Leblanc, Vincent, 1554-ca. 1640", "id": "5837", "pubLoc": "Amsterdam"}