{"imprint": "\"[S.l.], 1642\"", "pubYear": "1642", "imagePath": "/images/ned-kbn-all-00003778-002-0001R_96.jpg", "prqId": "ned-kbn-all-00003778-002", "language": "Dutch", "title": "Eene korte verklaringh van ses puncten. I. Van 't Bloedt en Water der Sielen. II. Van de ghenadighe verkiesingh ... III. Van de sonde ... IV. Hoe Christus het Rijck aen sijnen Vader sal over-geven? V. Van de Magia ... VI. Van 't Mysterio ... Door Jacob B\u00f6", "author": "B\u00f6hme, Jakob, 1575-1624", "id": "8762", "pubLoc": "s.l."}