{"status": "OK", "results": [{"geometry": {"location_type": "APPROXIMATE", "bounds": {"northeast": {"lat": 47.8155914, "lng": 9.6631962}, "southwest": {"lat": 47.7011635, "lng": 9.4836797}}, "viewport": {"northeast": {"lat": 47.8155914, "lng": 9.6631962}, "southwest": {"lat": 47.7011635, "lng": 9.4836797}}, "location": {"lat": 47.7782704, "lng": 9.612130299999999}}, "address_components": [{"long_name": "Ravensburg", "types": ["locality", "political"], "short_name": "Ravensburg"}, {"long_name": "Ravensburg", "types": ["administrative_area_level_3", "political"], "short_name": "RV"}, {"long_name": "T\u00fcbingen", "types": ["administrative_area_level_2", "political"], "short_name": "T\u00dc"}, {"long_name": "Baden-W\u00fcrttemberg", "types": ["administrative_area_level_1", "political"], "short_name": "BW"}, {"long_name": "Germany", "types": ["country", "political"], "short_name": "DE"}], "place_id": "ChIJjUNwkEypm0cR8LLfpbdrHwQ", "formatted_address": "Ravensburg, Germany", "types": ["locality", "political"]}]}