{"status": "OK", "results": [{"geometry": {"location_type": "APPROXIMATE", "bounds": {"northeast": {"lat": 47.130114, "lng": 2.472585}, "southwest": {"lat": 47.025962, "lng": 2.3240218}}, "viewport": {"northeast": {"lat": 47.130114, "lng": 2.472585}, "southwest": {"lat": 47.025962, "lng": 2.3240218}}, "location": {"lat": 47.081012, "lng": 2.398782}}, "address_components": [{"long_name": "Bourges", "types": ["locality", "political"], "short_name": "Bourges"}, {"long_name": "Cher", "types": ["administrative_area_level_2", "political"], "short_name": "Cher"}, {"long_name": "Centre", "types": ["administrative_area_level_1", "political"], "short_name": "Centre"}, {"long_name": "France", "types": ["country", "political"], "short_name": "FR"}], "place_id": "ChIJF7SbuHeW-kcRvoVczSwo-8s", "formatted_address": "Bourges, France", "types": ["locality", "political"]}]}