[{"languageId": 6, "classificationId": 15, "year": 1564, "lat": 41.902, "lng": 12.496, "id": 4347}, {"languageId": 6, "classificationId": 15, "year": 1564, "lat": 45.44, "lng": 12.315, "id": 4771}, {"languageId": 6, "classificationId": 15, "year": 1564, "lat": 41.902, "lng": 12.496, "id": 5405}, {"languageId": 6, "classificationId": 15, "year": 1672, "lat": 52.16, "lng": 4.497, "id": 6556}, {"languageId": 6, "classificationId": 15, "year": 1668, "lat": 52.37, "lng": 4.895, "id": 7067}, {"languageId": 6, "classificationId": 15, "year": 1674, "lat": 52.37, "lng": 4.895, "id": 8965}, {"languageId": 6, "classificationId": 15, "year": 1517, "lat": 45.764, "lng": 4.835, "id": 14547}, {"languageId": 3, "classificationId": 15, "year": 1692, "lat": 51.924, "lng": 4.477, "id": 22932}, {"languageId": 3, "classificationId": 15, "year": 1692, "lat": 51.924, "lng": 4.477, "id": 22943}, {"languageId": 3, "classificationId": 15, "year": 1692, "lat": 51.924, "lng": 4.477, "id": 22966}, {"languageId": 3, "classificationId": 15, "year": 1692, "lat": 51.924, "lng": 4.477, "id": 23204}, {"languageId": 3, "classificationId": 15, "year": 1692, "lat": 51.924, "lng": 4.477, "id": 23224}, {"languageId": 3, "classificationId": 15, "year": 1692, "lat": 51.924, "lng": 4.477, "id": 23268}, {"languageId": 3, "classificationId": 15, "year": 1692, "lat": 51.924, "lng": 4.477, "id": 24007}, {"languageId": 3, "classificationId": 15, "year": 1692, "lat": 51.924, "lng": 4.477, "id": 24019}, {"languageId": 3, "classificationId": 15, "year": 1692, "lat": 51.924, "lng": 4.477, "id": 24938}, {"languageId": 3, "classificationId": 15, "year": 1692, "lat": 51.924, "lng": 4.477, "id": 24951}, {"languageId": 6, "classificationId": 15, "year": 1677, "lat": 52.16, "lng": 4.497, "id": 25919}, {"languageId": 3, "classificationId": 15, "year": 1677, "lat": 51.837, "lng": 4.975, "id": 26543}, {"languageId": 6, "classificationId": 15, "year": 1680, "lat": 52.09, "lng": 5.121, "id": 34860}, {"languageId": 6, "classificationId": 15, "year": 1669, "lat": 52.266, "lng": 6.155, "id": 39463}, {"languageId": 6, "classificationId": 15, "year": 1570, "lat": 51.219, "lng": 4.402, "id": 39475}, {"languageId": 6, "classificationId": 15, "year": 1570, "lat": 51.219, "lng": 4.402, "id": 39787}, {"languageId": 6, "classificationId": 15, "year": 1669, "lat": 52.266, "lng": 6.155, "id": 39887}, {"languageId": 6, "classificationId": 15, "year": 1570, "lat": 51.219, "lng": 4.402, "id": 40008}, {"languageId": 6, "classificationId": 15, "year": 1595, "lat": 52.16, "lng": 4.497, "id": 40744}, {"languageId": 6, "classificationId": 15, "year": 1693, "lat": 51.924, "lng": 4.477, "id": 41597}]