[{"languageId": 6, "classificationId": 1, "year": 1567, "lat": 51.873, "lng": 12.627, "id": 66}, {"languageId": 6, "classificationId": 1, "year": 1586, "lat": 54.523, "lng": 9.563, "id": 185}, {"languageId": 6, "classificationId": 1, "year": 1576, "lat": 51.873, "lng": 12.627, "id": 209}, {"languageId": 5, "classificationId": 1, "year": 1562, "lat": 53.551, "lng": 9.993, "id": 1022}, {"languageId": 6, "classificationId": 1, "year": 1570, "lat": 51.873, "lng": 12.627, "id": 1159}, {"languageId": 6, "classificationId": 1, "year": 1598, "lat": 53.551, "lng": 9.993, "id": 1871}, {"languageId": 6, "classificationId": 1, "year": 1588, "lat": 51.873, "lng": 12.627, "id": 1999}, {"languageId": 6, "classificationId": 1, "year": 1588, "lat": 51.873, "lng": 12.627, "id": 2338}, {"languageId": 21, "classificationId": 1, "year": 1589, "lat": 51.873, "lng": 12.627, "id": 2557}, {"languageId": 6, "classificationId": 1, "year": 1562, "lat": 45.44, "lng": 12.315, "id": 2730}, {"languageId": 6, "classificationId": 1, "year": 1559, "lat": 45.44, "lng": 12.315, "id": 2851}, {"languageId": 6, "classificationId": 1, "year": 1480, "lat": 41.902, "lng": 12.496, "id": 4447}, {"languageId": 6, "classificationId": 1, "year": 1561, "lat": 45.44, "lng": 12.315, "id": 4665}, {"languageId": 6, "classificationId": 1, "year": 1559, "lat": 45.44, "lng": 12.315, "id": 5156}, {"languageId": 6, "classificationId": 1, "year": 1687, "lat": 52.16, "lng": 4.497, "id": 6962}, {"languageId": 6, "classificationId": 1, "year": 1639, "lat": 51.985, "lng": 5.898, "id": 7251}, {"languageId": 6, "classificationId": 1, "year": 1606, "lat": 52.16, "lng": 4.497, "id": 7389}, {"languageId": 6, "classificationId": 1, "year": 1625, "lat": 52.16, "lng": 4.497, "id": 8013}, {"languageId": 6, "classificationId": 1, "year": 1679, "lat": 52.16, "lng": 4.497, "id": 8036}, {"languageId": 6, "classificationId": 1, "year": 1695, "lat": 54.525, "lng": 15.255, "id": 8255}, {"languageId": 3, "classificationId": 1, "year": 1634, "lat": 54.525, "lng": 15.255, "id": 8340}, {"languageId": 6, "classificationId": 1, "year": 1651, "lat": 52.16, "lng": 4.497, "id": 8361}, {"languageId": 3, "classificationId": 1, "year": 1683, "lat": 51.924, "lng": 4.477, "id": 8389}, {"languageId": 3, "classificationId": 1, "year": 1504, "lat": 49.938, "lng": 2.818, "id": 8741}, {"languageId": 6, "classificationId": 1, "year": 1605, "lat": 52.16, "lng": 4.497, "id": 8899}, {"languageId": 6, "classificationId": 1, "year": 1607, "lat": 52.16, "lng": 4.497, "id": 9969}, {"languageId": 6, "classificationId": 1, "year": 1607, "lat": 52.37, "lng": 4.895, "id": 10274}, {"languageId": 6, "classificationId": 1, "year": 1687, "lat": 52.16, "lng": 4.497, "id": 12425}, {"languageId": 6, "classificationId": 1, "year": 1677, "lat": 48.573, "lng": 7.752, "id": 12506}, {"languageId": 6, "classificationId": 1, "year": 1677, "lat": 52.228, "lng": 11.009, "id": 12603}, {"languageId": 6, "classificationId": 1, "year": 1588, "lat": 53.551, "lng": 9.993, "id": 13064}, {"languageId": 6, "classificationId": 1, "year": 1493, "lat": 41.902, "lng": 12.496, "id": 13180}, {"languageId": 6, "classificationId": 1, "year": 1481, "lat": 41.902, "lng": 12.496, "id": 13597}, {"languageId": 6, "classificationId": 1, "year": 1484, "lat": 41.902, "lng": 12.496, "id": 13871}, {"languageId": 6, "classificationId": 1, "year": 1675, "lat": 52.228, "lng": 11.009, "id": 14066}, {"languageId": 6, "classificationId": 1, "year": 1582, "lat": 46.882, "lng": 8.642, "id": 14995}, {"languageId": 6, "classificationId": 1, "year": 1594, "lat": 51.339, "lng": 12.373, "id": 15002}, {"languageId": 6, "classificationId": 1, "year": 1582, "lat": 51.339, "lng": 12.373, "id": 15111}, {"languageId": 6, "classificationId": 1, "year": 1591, "lat": 51.339, "lng": 12.373, "id": 15154}, {"languageId": 6, "classificationId": 1, "year": 1582, "lat": 51.339, "lng": 12.373, "id": 15161}, {"languageId": 6, "classificationId": 1, "year": 1591, "lat": 51.339, "lng": 12.373, "id": 15169}, {"languageId": 6, "classificationId": 1, "year": 1588, "lat": 53.551, "lng": 9.993, "id": 15231}, {"languageId": 6, "classificationId": 1, "year": 1582, "lat": 51.339, "lng": 12.373, "id": 15318}, {"languageId": 6, "classificationId": 1, "year": 1581, "lat": 51.873, "lng": 12.627, "id": 15369}, {"languageId": 6, "classificationId": 1, "year": 1594, "lat": 51.339, "lng": 12.373, "id": 15421}, {"languageId": 6, "classificationId": 1, "year": 1590, "lat": 54.092, "lng": 12.099, "id": 15463}, {"languageId": 6, "classificationId": 1, "year": 1588, "lat": 51.339, "lng": 12.373, "id": 15496}, {"languageId": 6, "classificationId": 1, "year": 1591, "lat": 53.551, "lng": 9.993, "id": 15519}, {"languageId": 6, "classificationId": 1, "year": 1594, "lat": 51.339, "lng": 12.373, "id": 15574}, {"languageId": 6, "classificationId": 1, "year": 1607, "lat": 48.856, "lng": 2.352, "id": 18304}, {"languageId": 6, "classificationId": 1, "year": 1695, "lat": 52.16, "lng": 4.497, "id": 22466}, {"languageId": 6, "classificationId": 1, "year": 1666, "lat": 52.09, "lng": 5.121, "id": 23720}, {"languageId": 6, "classificationId": 1, "year": 1700, "lat": 53.188, "lng": 5.556, "id": 23981}, {"languageId": 6, "classificationId": 1, "year": 1609, "lat": 52.16, "lng": 4.497, "id": 24022}, {"languageId": 3, "classificationId": 1, "year": 1685, "lat": 54.525, "lng": 15.255, "id": 24173}, {"languageId": 6, "classificationId": 1, "year": 1685, "lat": 52.09, "lng": 5.121, "id": 24451}, {"languageId": 3, "classificationId": 1, "year": 1691, "lat": 51.924, "lng": 4.477, "id": 25535}, {"languageId": 3, "classificationId": 1, "year": 1679, "lat": 52.37, "lng": 4.895, "id": 25752}, {"languageId": 3, "classificationId": 1, "year": 1687, "lat": 52.07, "lng": 4.3, "id": 26116}, {"languageId": 3, "classificationId": 1, "year": 1609, "lat": 54.525, "lng": 15.255, "id": 26943}, {"languageId": 6, "classificationId": 1, "year": 1500, "lat": 54.525, "lng": 15.255, "id": 27399}, {"languageId": 6, "classificationId": 1, "year": 1657, "lat": 48.856, "lng": 2.352, "id": 30643}, {"languageId": 10, "classificationId": 1, "year": 1595, "lat": 49.443, "lng": 1.099, "id": 30858}, {"languageId": 10, "classificationId": 1, "year": 1584, "lat": 48.856, "lng": 2.352, "id": 31011}, {"languageId": 6, "classificationId": 1, "year": 1565, "lat": 48.856, "lng": 2.352, "id": 31034}, {"languageId": 10, "classificationId": 1, "year": 1551, "lat": 48.856, "lng": 2.352, "id": 31184}, {"languageId": 10, "classificationId": 1, "year": 1586, "lat": 48.856, "lng": 2.352, "id": 31378}, {"languageId": 6, "classificationId": 1, "year": 1550, "lat": 48.856, "lng": 2.352, "id": 31569}, {"languageId": 10, "classificationId": 1, "year": 1551, "lat": 48.856, "lng": 2.352, "id": 31716}, {"languageId": 10, "classificationId": 1, "year": 1586, "lat": 54.525, "lng": 15.255, "id": 31774}, {"languageId": 10, "classificationId": 1, "year": 1602, "lat": 48.856, "lng": 2.352, "id": 31780}, {"languageId": 10, "classificationId": 1, "year": 1586, "lat": 48.856, "lng": 2.352, "id": 31796}, {"languageId": 10, "classificationId": 1, "year": 1574, "lat": 48.856, "lng": 2.352, "id": 32349}, {"languageId": 10, "classificationId": 1, "year": 1550, "lat": 48.856, "lng": 2.352, "id": 32663}, {"languageId": 10, "classificationId": 1, "year": 1610, "lat": 48.856, "lng": 2.352, "id": 32772}, {"languageId": 10, "classificationId": 1, "year": 1604, "lat": 48.856, "lng": 2.352, "id": 33064}, {"languageId": 10, "classificationId": 1, "year": 1605, "lat": 48.856, "lng": 2.352, "id": 33150}, {"languageId": 10, "classificationId": 1, "year": 1603, "lat": 48.856, "lng": 2.352, "id": 33609}, {"languageId": 10, "classificationId": 1, "year": 1561, "lat": 48.856, "lng": 2.352, "id": 33683}, {"languageId": 10, "classificationId": 1, "year": 1590, "lat": 48.856, "lng": 2.352, "id": 33977}, {"languageId": 10, "classificationId": 1, "year": 1699, "lat": 49.376, "lng": 2.414, "id": 34059}, {"languageId": 10, "classificationId": 1, "year": 1550, "lat": 48.856, "lng": 2.352, "id": 34067}, {"languageId": 10, "classificationId": 1, "year": 1594, "lat": 48.856, "lng": 2.352, "id": 34259}, {"languageId": 6, "classificationId": 1, "year": 1562, "lat": 48.566, "lng": 13.431, "id": 35550}, {"languageId": 6, "classificationId": 1, "year": 1588, "lat": 51.339, "lng": 12.373, "id": 37176}, {"languageId": 6, "classificationId": 1, "year": 1609, "lat": 52.16, "lng": 4.497, "id": 39358}, {"languageId": 6, "classificationId": 1, "year": 1657, "lat": 52.16, "lng": 4.497, "id": 40183}, {"languageId": 6, "classificationId": 1, "year": 1677, "lat": 52.09, "lng": 5.121, "id": 40749}, {"languageId": 6, "classificationId": 1, "year": 1638, "lat": 52.16, "lng": 4.497, "id": 40897}, {"languageId": 3, "classificationId": 1, "year": 1679, "lat": 51.924, "lng": 4.477, "id": 41389}, {"languageId": 3, "classificationId": 1, "year": 1683, "lat": 51.924, "lng": 4.477, "id": 41439}, {"languageId": 3, "classificationId": 1, "year": 1609, "lat": 52.16, "lng": 4.497, "id": 41462}, {"languageId": 3, "classificationId": 1, "year": 1677, "lat": 52.387, "lng": 4.646, "id": 41631}]