[{"lat": 51.736, "lng": 12.609, "languageId": 17, "id": 130, "classificationId": 4}, {"lat": 51.602, "lng": 12.457, "languageId": 17, "id": 567, "classificationId": 35}, {"lat": 51.784, "lng": 12.922, "languageId": 17, "id": 765, "classificationId": 18}, {"lat": 53.954, "lng": 11.944, "languageId": 17, "id": 819, "classificationId": ""}, {"lat": 51.75, "lng": 12.587, "languageId": 17, "id": 1276, "classificationId": 35}, {"lat": 53.661, "lng": 9.804, "languageId": 17, "id": 1567, "classificationId": ""}, {"lat": 51.837, "lng": 12.334, "languageId": 17, "id": 2100, "classificationId": 6}, {"lat": 53.808, "lng": 11.813, "languageId": 17, "id": 2500, "classificationId": ""}, {"lat": 45.473, "lng": 12.018, "languageId": 17, "id": 2626, "classificationId": 35}, {"lat": 45.169, "lng": 12.305, "languageId": 17, "id": 2649, "classificationId": 31}, {"lat": 45.592, "lng": 12.218, "languageId": 17, "id": 2682, "classificationId": 35}, {"lat": 43.643, "lng": 11.379, "languageId": 17, "id": 2778, "classificationId": 18}, {"lat": 45.621, "lng": 12.318, "languageId": 17, "id": 2784, "classificationId": 14}, {"lat": 45.183, "lng": 12.258, "languageId": 17, "id": 2799, "classificationId": 4}, {"lat": 45.319, "lng": 12.53, "languageId": 17, "id": 2866, "classificationId": 24}, {"lat": 45.227, "lng": 12.027, "languageId": 17, "id": 2890, "classificationId": 35}, {"lat": 45.445, "lng": 12.514, "languageId": 17, "id": 2935, "classificationId": 12}, {"lat": 45.408, "lng": 12.489, "languageId": 17, "id": 2943, "classificationId": 35}, {"lat": 45.152, "lng": 12.436, "languageId": 17, "id": 3062, "classificationId": 12}, {"lat": 45.357, "lng": 12.194, "languageId": 17, "id": 3100, "classificationId": 4}, {"lat": 45.154, "lng": 12.134, "languageId": 17, "id": 3162, "classificationId": 28}, {"lat": 45.148, "lng": 12.259, "languageId": 17, "id": 3190, "classificationId": 2}, {"lat": 45.475, "lng": 12.031, "languageId": 17, "id": 3243, "classificationId": 35}, {"lat": 45.584, "lng": 12.203, "languageId": 17, "id": 3273, "classificationId": ""}, {"lat": 43.881, "lng": 11.229, "languageId": 17, "id": 3327, "classificationId": 4}, {"lat": 45.471, "lng": 12.159, "languageId": 17, "id": 3370, "classificationId": 4}, {"lat": 45.249, "lng": 12.216, "languageId": 17, "id": 3421, "classificationId": 12}, {"lat": 45.614, "lng": 9.155, "languageId": 17, "id": 3430, "classificationId": 35}, {"lat": 45.614, "lng": 12.024, "languageId": 17, "id": 3472, "classificationId": 18}, {"lat": 45.479, "lng": 12.28, "languageId": 17, "id": 3480, "classificationId": 18}, {"lat": 45.36, "lng": 9.111, "languageId": 17, "id": 3485, "classificationId": ""}, {"lat": 45.687, "lng": 9.009, "languageId": 17, "id": 3621, "classificationId": 25}, {"lat": 52.449, "lng": 5.111, "languageId": 17, "id": 6765, "classificationId": 35}, {"lat": 47.62, "lng": 7.354, "languageId": 17, "id": 10735, "classificationId": 21}, {"lat": 48.698, "lng": 2.065, "languageId": 17, "id": 10861, "classificationId": 35}, {"lat": 48.747, "lng": 2.076, "languageId": 17, "id": 11186, "classificationId": 20}, {"lat": 47.463, "lng": 7.372, "languageId": 17, "id": 11326, "classificationId": 8}, {"lat": 47.401, "lng": 7.718, "languageId": 17, "id": 11353, "classificationId": 21}, {"lat": 48.854, "lng": 2.432, "languageId": 17, "id": 11481, "classificationId": 21}, {"lat": 44.253, "lng": 11.092, "languageId": 17, "id": 11598, "classificationId": 20}, {"lat": 48.601, "lng": 2.53, "languageId": 17, "id": 11727, "classificationId": 20}, {"lat": 48.781, "lng": 2.327, "languageId": 17, "id": 11860, "classificationId": 21}, {"lat": 48.957, "lng": 2.286, "languageId": 17, "id": 11961, "classificationId": 20}, {"lat": 48.748, "lng": 2.237, "languageId": 17, "id": 12072, "classificationId": 21}, {"lat": 51.484, "lng": 4.696, "languageId": 17, "id": 12263, "classificationId": 6}, {"lat": 39.487, "lng": -0.543, "languageId": 17, "id": 12281, "classificationId": 21}, {"lat": 47.708, "lng": 7.522, "languageId": 17, "id": 12698, "classificationId": 35}, {"lat": 52.165, "lng": 5.863, "languageId": 17, "id": 12705, "classificationId": 35}, {"lat": 43.976, "lng": 11.108, "languageId": 17, "id": 12724, "classificationId": 35}, {"lat": 47.313, "lng": 7.451, "languageId": 17, "id": 12759, "classificationId": 21}, {"lat": 48.204, "lng": 11.07, "languageId": 17, "id": 13254, "classificationId": 4}, {"lat": 47.603, "lng": 7.624, "languageId": 17, "id": 13300, "classificationId": 21}, {"lat": 47.858, "lng": 7.681, "languageId": 17, "id": 13475, "classificationId": 28}, {"lat": 47.391, "lng": 7.682, "languageId": 17, "id": 13555, "classificationId": 21}, {"lat": 41.73, "lng": 12.283, "languageId": 17, "id": 13591, "classificationId": 35}, {"lat": 51.709, "lng": -1.537, "languageId": 17, "id": 13746, "classificationId": 35}, {"lat": 47.63, "lng": 7.529, "languageId": 17, "id": 13753, "classificationId": 21}, {"lat": 49.033, "lng": 2.076, "languageId": 17, "id": 13810, "classificationId": ""}, {"lat": 52.147, "lng": 4.253, "languageId": 17, "id": 13947, "classificationId": 4}, {"lat": 41.755, "lng": 12.56, "languageId": 17, "id": 14001, "classificationId": 35}, {"lat": 50.993, "lng": 4.252, "languageId": 17, "id": 14268, "classificationId": ""}, {"lat": 47.462, "lng": 7.421, "languageId": 17, "id": 14483, "classificationId": 35}, {"lat": 48.801, "lng": 2.484, "languageId": 17, "id": 14629, "classificationId": 13}, {"lat": 43.8, "lng": 11.452, "languageId": 17, "id": 14672, "classificationId": 4}, {"lat": 42.046, "lng": 12.35, "languageId": 17, "id": 14887, "classificationId": 14}, {"lat": 53.903, "lng": 12.074, "languageId": 17, "id": 15301, "classificationId": ""}, {"lat": 54.333, "lng": 12.323, "languageId": 17, "id": 15553, "classificationId": 18}, {"lat": 47.68, "lng": 7.496, "languageId": 17, "id": 16084, "classificationId": 35}, {"lat": 54.354, "lng": 14.978, "languageId": 17, "id": 16786, "classificationId": 35}, {"lat": 49.818, "lng": 8.576, "languageId": 17, "id": 17814, "classificationId": 4}, {"lat": 41.938, "lng": 12.573, "languageId": 17, "id": 17821, "classificationId": 35}, {"lat": 52.442, "lng": 4.773, "languageId": 17, "id": 18226, "classificationId": ""}, {"lat": 47.549, "lng": 7.679, "languageId": 17, "id": 18227, "classificationId": 4}, {"lat": 47.382, "lng": 7.293, "languageId": 17, "id": 18246, "classificationId": 35}, {"lat": 47.446, "lng": 7.65, "languageId": 17, "id": 18291, "classificationId": 4}, {"lat": 41.886, "lng": 12.372, "languageId": 17, "id": 18373, "classificationId": ""}, {"lat": 43.84, "lng": 1.547, "languageId": 17, "id": 18442, "classificationId": 12}, {"lat": 47.557, "lng": 7.302, "languageId": 17, "id": 18469, "classificationId": 28}, {"lat": 48.702, "lng": 2.225, "languageId": 17, "id": 18607, "classificationId": 18}, {"lat": 51.378, "lng": 4.564, "languageId": 17, "id": 18687, "classificationId": 24}, {"lat": 49.108, "lng": 2.551, "languageId": 17, "id": 18718, "classificationId": 6}, {"lat": 47.526, "lng": 7.744, "languageId": 17, "id": 18870, "classificationId": 21}, {"lat": 51.973, "lng": 4.479, "languageId": 17, "id": 18985, "classificationId": 4}, {"lat": 51.372, "lng": 4.442, "languageId": 17, "id": 19704, "classificationId": 6}, {"lat": 49.152, "lng": 2.628, "languageId": 17, "id": 19722, "classificationId": 35}, {"lat": 48.885, "lng": 2.352, "languageId": 17, "id": 19921, "classificationId": 35}, {"lat": 47.701, "lng": 7.525, "languageId": 17, "id": 20142, "classificationId": 21}, {"lat": 48.658, "lng": 2.482, "languageId": 17, "id": 20255, "classificationId": 21}, {"lat": 52.343, "lng": 4.271, "languageId": 17, "id": 23440, "classificationId": 6}, {"lat": 48.847, "lng": 2.619, "languageId": 17, "id": 28440, "classificationId": 35}, {"lat": 47.828, "lng": 7.344, "languageId": 17, "id": 29496, "classificationId": 21}, {"lat": 47.373, "lng": 7.772, "languageId": 17, "id": 29909, "classificationId": 21}, {"lat": 48.594, "lng": 2.233, "languageId": 17, "id": 30575, "classificationId": 6}, {"lat": 45.621, "lng": 4.791, "languageId": 17, "id": 30756, "classificationId": 4}, {"lat": 48.916, "lng": 2.232, "languageId": 17, "id": 30963, "classificationId": 4}, {"lat": 48.95, "lng": 2.238, "languageId": 17, "id": 31231, "classificationId": ""}, {"lat": 48.394, "lng": 7.808, "languageId": 17, "id": 32658, "classificationId": 3}, {"lat": 49.025, "lng": 2.486, "languageId": 17, "id": 32666, "classificationId": 4}, {"lat": 45.601, "lng": 4.737, "languageId": 17, "id": 33015, "classificationId": 4}, {"lat": 52.081, "lng": 4.777, "languageId": 17, "id": 34843, "classificationId": 8}, {"lat": 52.403, "lng": 5.142, "languageId": 17, "id": 36093, "classificationId": 21}, {"lat": 59.884, "lng": 17.681, "languageId": 17, "id": 36273, "classificationId": ""}, {"lat": 53.482, "lng": 5.635, "languageId": 17, "id": 38055, "classificationId": 18}, {"lat": 52.979, "lng": 5.563, "languageId": 17, "id": 39077, "classificationId": 34}]